Metadata-Version: 1.0
Name: asif-alam-distributions
Version: 0.1
Summary: Gaussian and binomial distributions
Home-page: UNKNOWN
Author: Asif Alam
Author-email: UNKNOWN
License: UNKNOWN
Platform: UNKNOWN
